// class version 55.0 (55)
// access flags 0x21
public class GenFactorial {

  // compiled from: GenFactorial.java

  // access flags 0x1
  public <init>()V
   L0
    LINENUMBER 29 L0
    ALOAD 0
    INVOKESPECIAL java/lang/Object.<init> ()V
    RETURN
   L1
    LOCALVARIABLE this LGenFactorial; L0 L1 0
    MAXSTACK = 1
    MAXLOCALS = 1

  // access flags 0x9
  public static main([Ljava/lang/String;)V
   L0
    LINENUMBER 32 L0
    NEW jminusminus/CLEmitter
    DUP
    ICONST_1
    INVOKESPECIAL jminusminus/CLEmitter.<init> (Z)V
    ASTORE 1
   L1
    LINENUMBER 35 L1
    NEW java/util/ArrayList
    DUP
    INVOKESPECIAL java/util/ArrayList.<init> ()V
    ASTORE 2
   L2
    LINENUMBER 38 L2
    ALOAD 2
    LDC "public"
    INVOKEVIRTUAL java/util/ArrayList.add (Ljava/lang/Object;)Z
    POP
   L3
    LINENUMBER 39 L3
    ALOAD 1
    ALOAD 2
    LDC "Factorial"
    LDC "java/lang/Object"
    ACONST_NULL
    ICONST_1
    INVOKEVIRTUAL jminusminus/CLEmitter.addClass (Ljava/util/ArrayList;Ljava/lang/String;Ljava/lang/String;Ljava/util/ArrayList;Z)V
   L4
    LINENUMBER 42 L4
    ALOAD 2
    INVOKEVIRTUAL java/util/ArrayList.clear ()V
   L5
    LINENUMBER 43 L5
    ALOAD 2
    LDC "public"
    INVOKEVIRTUAL java/util/ArrayList.add (Ljava/lang/Object;)Z
    POP
   L6
    LINENUMBER 44 L6
    ALOAD 2
    LDC "static"
    INVOKEVIRTUAL java/util/ArrayList.add (Ljava/lang/Object;)Z
    POP
   L7
    LINENUMBER 45 L7
    ALOAD 1
    ALOAD 2
    LDC "main"
    LDC "([Ljava/lang/String;)V"
    ACONST_NULL
    ICONST_1
    INVOKEVIRTUAL jminusminus/CLEmitter.addMethod (Ljava/util/ArrayList;Ljava/lang/String;Ljava/lang/String;Ljava/util/ArrayList;Z)V
   L8
    LINENUMBER 48 L8
    ALOAD 1
    BIPUSH 42
    INVOKEVIRTUAL jminusminus/CLEmitter.addNoArgInstruction (I)V
   L9
    LINENUMBER 49 L9
    ALOAD 1
    ICONST_3
    INVOKEVIRTUAL jminusminus/CLEmitter.addNoArgInstruction (I)V
   L10
    LINENUMBER 50 L10
    ALOAD 1
    BIPUSH 50
    INVOKEVIRTUAL jminusminus/CLEmitter.addNoArgInstruction (I)V
   L11
    LINENUMBER 51 L11
    ALOAD 1
    SIPUSH 184
    LDC "java/lang/Integer"
    LDC "parseInt"
    LDC "(Ljava/lang/String;)I"
    INVOKEVIRTUAL jminusminus/CLEmitter.addMemberAccessInstruction (ILjava/lang/String;Ljava/lang/String;Ljava/lang/String;)V
   L12
    LINENUMBER 53 L12
    ALOAD 1
    BIPUSH 60
    INVOKEVIRTUAL jminusminus/CLEmitter.addNoArgInstruction (I)V
   L13
    LINENUMBER 56 L13
    ALOAD 1
    BIPUSH 27
    INVOKEVIRTUAL jminusminus/CLEmitter.addNoArgInstruction (I)V
   L14
    LINENUMBER 57 L14
    ALOAD 1
    SIPUSH 184
    LDC "Factorial"
    LDC "factorial"
    LDC "(I)I"
    INVOKEVIRTUAL jminusminus/CLEmitter.addMemberAccessInstruction (ILjava/lang/String;Ljava/lang/String;Ljava/lang/String;)V
   L15
    LINENUMBER 58 L15
    ALOAD 1
    BIPUSH 61
    INVOKEVIRTUAL jminusminus/CLEmitter.addNoArgInstruction (I)V
   L16
    LINENUMBER 63 L16
    ALOAD 1
    SIPUSH 178
    LDC "java/lang/System"
    LDC "out"
    LDC "Ljava/io/PrintStream;"
    INVOKEVIRTUAL jminusminus/CLEmitter.addMemberAccessInstruction (ILjava/lang/String;Ljava/lang/String;Ljava/lang/String;)V
   L17
    LINENUMBER 67 L17
    ALOAD 1
    SIPUSH 187
    LDC "java/lang/StringBuffer"
    INVOKEVIRTUAL jminusminus/CLEmitter.addReferenceInstruction (ILjava/lang/String;)V
   L18
    LINENUMBER 68 L18
    ALOAD 1
    BIPUSH 89
    INVOKEVIRTUAL jminusminus/CLEmitter.addNoArgInstruction (I)V
   L19
    LINENUMBER 69 L19
    ALOAD 1
    SIPUSH 183
    LDC "java/lang/StringBuffer"
    LDC "<init>"
    LDC "()V"
    INVOKEVIRTUAL jminusminus/CLEmitter.addMemberAccessInstruction (ILjava/lang/String;Ljava/lang/String;Ljava/lang/String;)V
   L20
    LINENUMBER 72 L20
    ALOAD 1
    BIPUSH 27
    INVOKEVIRTUAL jminusminus/CLEmitter.addNoArgInstruction (I)V
   L21
    LINENUMBER 73 L21
    ALOAD 1
    SIPUSH 182
    LDC "java/lang/StringBuffer"
    LDC "append"
    LDC "(I)Ljava/lang/StringBuffer;"
    INVOKEVIRTUAL jminusminus/CLEmitter.addMemberAccessInstruction (ILjava/lang/String;Ljava/lang/String;Ljava/lang/String;)V
   L22
    LINENUMBER 77 L22
    ALOAD 1
    LDC "! = "
    INVOKEVIRTUAL jminusminus/CLEmitter.addLDCInstruction (Ljava/lang/String;)V
   L23
    LINENUMBER 78 L23
    ALOAD 1
    SIPUSH 182
    LDC "java/lang/StringBuffer"
    LDC "append"
    LDC "(Ljava/lang/String;)Ljava/lang/StringBuffer;"
    INVOKEVIRTUAL jminusminus/CLEmitter.addMemberAccessInstruction (ILjava/lang/String;Ljava/lang/String;Ljava/lang/String;)V
   L24
    LINENUMBER 82 L24
    ALOAD 1
    BIPUSH 28
    INVOKEVIRTUAL jminusminus/CLEmitter.addNoArgInstruction (I)V
   L25
    LINENUMBER 83 L25
    ALOAD 1
    SIPUSH 182
    LDC "java/lang/StringBuffer"
    LDC "append"
    LDC "(I)Ljava/lang/StringBuffer;"
    INVOKEVIRTUAL jminusminus/CLEmitter.addMemberAccessInstruction (ILjava/lang/String;Ljava/lang/String;Ljava/lang/String;)V
   L26
    LINENUMBER 87 L26
    ALOAD 1
    SIPUSH 182
    LDC "java/lang/StringBuffer"
    LDC "toString"
    LDC "()Ljava/lang/String;"
    INVOKEVIRTUAL jminusminus/CLEmitter.addMemberAccessInstruction (ILjava/lang/String;Ljava/lang/String;Ljava/lang/String;)V
   L27
    LINENUMBER 89 L27
    ALOAD 1
    SIPUSH 182
    LDC "java/io/PrintStream"
    LDC "println"
    LDC "(Ljava/lang/String;)V"
    INVOKEVIRTUAL jminusminus/CLEmitter.addMemberAccessInstruction (ILjava/lang/String;Ljava/lang/String;Ljava/lang/String;)V
   L28
    LINENUMBER 93 L28
    ALOAD 1
    SIPUSH 177
    INVOKEVIRTUAL jminusminus/CLEmitter.addNoArgInstruction (I)V
   L29
    LINENUMBER 96 L29
    ALOAD 2
    INVOKEVIRTUAL java/util/ArrayList.clear ()V
   L30
    LINENUMBER 97 L30
    ALOAD 2
    LDC "private"
    INVOKEVIRTUAL java/util/ArrayList.add (Ljava/lang/Object;)Z
    POP
   L31
    LINENUMBER 98 L31
    ALOAD 2
    LDC "static"
    INVOKEVIRTUAL java/util/ArrayList.add (Ljava/lang/Object;)Z
    POP
   L32
    LINENUMBER 99 L32
    ALOAD 1
    ALOAD 2
    LDC "factorial"
    LDC "(I)I"
    ACONST_NULL
    ICONST_1
    INVOKEVIRTUAL jminusminus/CLEmitter.addMethod (Ljava/util/ArrayList;Ljava/lang/String;Ljava/lang/String;Ljava/util/ArrayList;Z)V
   L33
    LINENUMBER 102 L33
    ALOAD 1
    BIPUSH 26
    INVOKEVIRTUAL jminusminus/CLEmitter.addNoArgInstruction (I)V
   L34
    LINENUMBER 103 L34
    ALOAD 1
    ICONST_4
    INVOKEVIRTUAL jminusminus/CLEmitter.addNoArgInstruction (I)V
   L35
    LINENUMBER 104 L35
    ALOAD 1
    SIPUSH 163
    LDC "Recurse"
    INVOKEVIRTUAL jminusminus/CLEmitter.addBranchInstruction (ILjava/lang/String;)V
   L36
    LINENUMBER 107 L36
    ALOAD 1
    ICONST_4
    INVOKEVIRTUAL jminusminus/CLEmitter.addNoArgInstruction (I)V
   L37
    LINENUMBER 108 L37
    ALOAD 1
    SIPUSH 172
    INVOKEVIRTUAL jminusminus/CLEmitter.addNoArgInstruction (I)V
   L38
    LINENUMBER 111 L38
    ALOAD 1
    LDC "Recurse"
    INVOKEVIRTUAL jminusminus/CLEmitter.addLabel (Ljava/lang/String;)V
   L39
    LINENUMBER 112 L39
    ALOAD 1
    BIPUSH 26
    INVOKEVIRTUAL jminusminus/CLEmitter.addNoArgInstruction (I)V
   L40
    LINENUMBER 113 L40
    ALOAD 1
    BIPUSH 26
    INVOKEVIRTUAL jminusminus/CLEmitter.addNoArgInstruction (I)V
   L41
    LINENUMBER 114 L41
    ALOAD 1
    ICONST_4
    INVOKEVIRTUAL jminusminus/CLEmitter.addNoArgInstruction (I)V
   L42
    LINENUMBER 115 L42
    ALOAD 1
    BIPUSH 100
    INVOKEVIRTUAL jminusminus/CLEmitter.addNoArgInstruction (I)V
   L43
    LINENUMBER 116 L43
    ALOAD 1
    SIPUSH 184
    LDC "Factorial"
    LDC "factorial"
    LDC "(I)I"
    INVOKEVIRTUAL jminusminus/CLEmitter.addMemberAccessInstruction (ILjava/lang/String;Ljava/lang/String;Ljava/lang/String;)V
   L44
    LINENUMBER 117 L44
    ALOAD 1
    BIPUSH 104
    INVOKEVIRTUAL jminusminus/CLEmitter.addNoArgInstruction (I)V
   L45
    LINENUMBER 118 L45
    ALOAD 1
    SIPUSH 172
    INVOKEVIRTUAL jminusminus/CLEmitter.addNoArgInstruction (I)V
   L46
    LINENUMBER 121 L46
    ALOAD 1
    INVOKEVIRTUAL jminusminus/CLEmitter.write ()V
   L47
    LINENUMBER 122 L47
    RETURN
   L48
    LOCALVARIABLE args [Ljava/lang/String; L0 L48 0
    LOCALVARIABLE e Ljminusminus/CLEmitter; L1 L48 1
    LOCALVARIABLE modifiers Ljava/util/ArrayList; L2 L48 2
    // signature Ljava/util/ArrayList<Ljava/lang/String;>;
    // declaration: modifiers extends java.util.ArrayList<java.lang.String>
    MAXSTACK = 6
    MAXLOCALS = 3
}
