// class version 55.0 (55)
// access flags 0x21
public class Try {

  // compiled from: Try.java
  // access flags 0x19
  public final static INNERCLASS java/lang/invoke/MethodHandles$Lookup java/lang/invoke/MethodHandles Lookup

  // access flags 0x1
  public <init>()V
   L0
    LINENUMBER 3 L0
    ALOAD 0
    INVOKESPECIAL java/lang/Object.<init> ()V
    RETURN
   L1
    LOCALVARIABLE this LTry; L0 L1 0
    MAXSTACK = 1
    MAXLOCALS = 1

  // access flags 0x9
  public static main([Ljava/lang/String;)V
   L0
    LINENUMBER 5 L0
    ALOAD 0
    ICONST_0
    AALOAD
    INVOKESTATIC java/lang/Integer.parseInt (Ljava/lang/String;)I
    ISTORE 1
   L1
    LINENUMBER 6 L1
    ILOAD 1
    INVOKESTATIC Try.isPrime (I)Z
    ISTORE 2
   L2
    LINENUMBER 7 L2
    ILOAD 2
    IFEQ L3
   L4
    LINENUMBER 8 L4
    GETSTATIC java/lang/System.out : Ljava/io/PrintStream;
    ILOAD 1
    INVOKEDYNAMIC makeConcatWithConstants(I)Ljava/lang/String; [
      // handle kind 0x6 : INVOKESTATIC
      java/lang/invoke/StringConcatFactory.makeConcatWithConstants(Ljava/lang/invoke/MethodHandles$Lookup;Ljava/lang/String;Ljava/lang/invoke/MethodType;Ljava/lang/String;[Ljava/lang/Object;)Ljava/lang/invoke/CallSite;
      // arguments:
      "\u0001 is a prime number"
    ]
    INVOKEVIRTUAL java/io/PrintStream.println (Ljava/lang/String;)V
    GOTO L5
   L3
    LINENUMBER 10 L3
   FRAME APPEND [I I]
    GETSTATIC java/lang/System.out : Ljava/io/PrintStream;
    ILOAD 1
    INVOKEDYNAMIC makeConcatWithConstants(I)Ljava/lang/String; [
      // handle kind 0x6 : INVOKESTATIC
      java/lang/invoke/StringConcatFactory.makeConcatWithConstants(Ljava/lang/invoke/MethodHandles$Lookup;Ljava/lang/String;Ljava/lang/invoke/MethodType;Ljava/lang/String;[Ljava/lang/Object;)Ljava/lang/invoke/CallSite;
      // arguments:
      "\u0001 is not a prime number"
    ]
    INVOKEVIRTUAL java/io/PrintStream.println (Ljava/lang/String;)V
   L5
    LINENUMBER 12 L5
   FRAME SAME
    RETURN
   L6
    LOCALVARIABLE args [Ljava/lang/String; L0 L6 0
    LOCALVARIABLE n I L1 L6 1
    LOCALVARIABLE result Z L2 L6 2
    MAXSTACK = 2
    MAXLOCALS = 3

  // access flags 0xA
  private static isPrime(I)Z
   L0
    LINENUMBER 16 L0
    ILOAD 0
    ICONST_2
    IF_ICMPGE L1
   L2
    LINENUMBER 17 L2
    ICONST_0
    IRETURN
   L1
    LINENUMBER 19 L1
   FRAME SAME
    ICONST_2
    ISTORE 1
   L3
   FRAME APPEND [I]
    ILOAD 1
    ILOAD 0
    ILOAD 1
    IDIV
    IF_ICMPGT L4
   L5
    LINENUMBER 20 L5
    ILOAD 0
    ILOAD 1
    IREM
    IFNE L6
   L7
    LINENUMBER 21 L7
    ICONST_0
    IRETURN
   L6
    LINENUMBER 19 L6
   FRAME SAME
    IINC 1 1
    GOTO L3
   L4
    LINENUMBER 24 L4
   FRAME CHOP 1
    ICONST_1
    IRETURN
   L8
    LOCALVARIABLE i I L3 L4 1
    LOCALVARIABLE n I L0 L8 0
    MAXSTACK = 3
    MAXLOCALS = 2
}
