public synthetic class IsPrime {


  // access flags 0x1009
  public static synthetic main([Ljava/lang/String;)V
    ALOAD 0
    ICONST_0
    AALOAD
    INVOKESTATIC java/lang/Integer.parseInt (Ljava/lang/String;)I
    ISTORE 1
    ILOAD 1
    INVOKESTATIC IsPrime.isPrime (I)Z
    ISTORE 2
    ILOAD 2
    IFEQ L0
    NEW java/lang/StringBuffer
    DUP
    INVOKESPECIAL java/lang/StringBuffer.<init> ()V
    ILOAD 1
    INVOKEVIRTUAL java/lang/StringBuffer.append (I)Ljava/lang/StringBuffer;
    LDC " is a prime number"
    INVOKEVIRTUAL java/lang/StringBuffer.append (I)Ljava/lang/StringBuffer;
    INVOKEVIRTUAL java/lang/StringBuffer.toString ()Ljava/lang/String;
    INVOKEVIRTUAL java/io/PrintStream.println (Ljava/lang/String;)V
    GOTO L1
   L0
    NEW java/lang/StringBuffer
    DUP
    INVOKESPECIAL java/lang/StringBuffer.<init> ()V
    ILOAD 1
    INVOKEVIRTUAL java/lang/StringBuffer.append (I)Ljava/lang/StringBuffer;
    LDC " is not a prime number"
    INVOKEVIRTUAL java/lang/StringBuffer.append (I)Ljava/lang/StringBuffer;
    INVOKEVIRTUAL java/lang/StringBuffer.toString ()Ljava/lang/String;
    INVOKEVIRTUAL java/io/PrintStream.println (Ljava/lang/String;)V
    GOTO L1
   L1
    RETURN
    MAXSTACK = 2
    MAXLOCALS = 3

  // access flags 0x100A
  private static synthetic isPrime(I)Z
    ILOAD 0
    ICONST_2
    IF_ICMPGE L0
    ICONST_0
    IRETURN
   L0
    ICONST_2
    ISTORE 1
   L1
    ILOAD 1
    ILOAD 0
    ILOAD 1
    IDIV
    IF_ICMPGT L2
    ICONST_0
    ILOAD 1
    IREM
    IFNE L3
    ICONST_0
    IRETURN
   L3
    IINC 1 1
    ICONST_1
    GOTO L1
   L2
    ICONST_1
    IRETURN
    MAXSTACK = 4
    MAXLOCALS = 2
}

private static boolean isPrime(int n) {
 *         if (n < 2) {
 *             return false;
 *         }
 *         for (int i = 2; i <= n / i; i++) {
 *             if (n % i == 0) {
 *                 return false;
 *             }
 *         }
 *         return true;
 *     }
 * }